nrtk/__init__.py
nrtk/impls/__init__.py
nrtk/impls/gen_object_detector_blackbox_response/__init__.py
nrtk/impls/gen_object_detector_blackbox_response/simple_generic_generator.py
nrtk/impls/gen_object_detector_blackbox_response/simple_pybsm_generator.py
nrtk/impls/image_metric/__init__.py
nrtk/impls/image_metric/niirs_image_metric.py
nrtk/impls/image_metric/snr_image_metric.py
nrtk/impls/perturb_image/__init__.py
nrtk/impls/perturb_image/generic/PIL/__init__.py
nrtk/impls/perturb_image/generic/PIL/enhance.py
nrtk/impls/perturb_image/generic/__init__.py
nrtk/impls/perturb_image/generic/albumentations_perturber.py
nrtk/impls/perturb_image/generic/compose_perturber.py
nrtk/impls/perturb_image/generic/cv2/__init__.py
nrtk/impls/perturb_image/generic/cv2/blur.py
nrtk/impls/perturb_image/generic/diffusion_perturber.py
nrtk/impls/perturb_image/generic/haze_perturber.py
nrtk/impls/perturb_image/generic/nop_perturber.py
nrtk/impls/perturb_image/generic/radial_distortion_perturber.py
nrtk/impls/perturb_image/generic/random_crop_perturber.py
nrtk/impls/perturb_image/generic/random_rotation_perturber.py
nrtk/impls/perturb_image/generic/random_scale_perturber.py
nrtk/impls/perturb_image/generic/random_translation_perturber.py
nrtk/impls/perturb_image/generic/skimage/__init__.py
nrtk/impls/perturb_image/generic/skimage/random_noise.py
nrtk/impls/perturb_image/generic/water_droplet_perturber.py
nrtk/impls/perturb_image/pybsm/__init__.py
nrtk/impls/perturb_image/pybsm/circular_aperture_otf_perturber.py
nrtk/impls/perturb_image/pybsm/defocus_otf_perturber.py
nrtk/impls/perturb_image/pybsm/detector_otf_perturber.py
nrtk/impls/perturb_image/pybsm/jitter_otf_perturber.py
nrtk/impls/perturb_image/pybsm/pybsm_otf_perturber.py
nrtk/impls/perturb_image/pybsm/pybsm_perturber.py
nrtk/impls/perturb_image/pybsm/scenario.py
nrtk/impls/perturb_image/pybsm/sensor.py
nrtk/impls/perturb_image/pybsm/turbulence_aperture_otf_perturber.py
nrtk/impls/perturb_image/pybsm/utils.py
nrtk-0.26.0.dist-info/LICENSE
nrtk-0.26.0.dist-info/METADATA
nrtk-0.26.0.dist-info/WHEEL
nrtk-0.26.0.dist-info/entry_points.txt
nrtk-0.26.0.dist-info/RECORD
