Metadata-Version: 2.1
Name: nrtk
Version: 0.26.0
Summary: Natural Robustness Toolkit (NRTK) is a platform for generating validated, sensor-specific perturbations and transformations used to evaluate the robustness of computer vision models.
License: Apache-2.0
Author: Kitware, Inc.
Author-email: nrtk@kitware.com
Requires-Python: >=3.10,<3.14
Classifier: Development Status :: 3 - Alpha
Classifier: Intended Audience :: Developers
Classifier: Intended Audience :: Science/Research
Classifier: License :: OSI Approved :: Apache Software License
Classifier: Operating System :: MacOS :: MacOS X
Classifier: Operating System :: Unix
Classifier: Programming Language :: Python :: 3
Classifier: Programming Language :: Python :: 3.10
Classifier: Programming Language :: Python :: 3.11
Classifier: Programming Language :: Python :: 3.12
Classifier: Programming Language :: Python :: 3.13
Provides-Extra: albumentations
Provides-Extra: diffusion
Provides-Extra: graphics
Provides-Extra: headless
Provides-Extra: maite
Provides-Extra: notebook-testing
Provides-Extra: pillow
Provides-Extra: pybsm
Provides-Extra: scikit-image
Provides-Extra: tools
Provides-Extra: waterdroplet
Requires-Dist: Pillow (>=10.3.0) ; extra == "tools" or extra == "pillow" or extra == "diffusion"
Requires-Dist: accelerate (>=0.20.0) ; extra == "diffusion"
Requires-Dist: albumentations (>=2.0.0) ; extra == "albumentations" or extra == "notebook-testing"
Requires-Dist: datasets (>=3.3.2) ; extra == "notebook-testing"
Requires-Dist: diffusers (>=0.21.0) ; extra == "diffusion"
Requires-Dist: fastapi (>=0.110.0) ; extra == "maite"
Requires-Dist: geopandas (>=0.14,<0.15) ; extra == "waterdroplet"
Requires-Dist: jupytext (>=1.16.7) ; extra == "notebook-testing"
Requires-Dist: kwcoco (>=0.2.18) ; extra == "tools"
Requires-Dist: lazy-loader (>=0.4)
Requires-Dist: maite (>=0.8.2,<0.9.0) ; extra == "maite"
Requires-Dist: matplotlib (>=3.7.1) ; extra == "notebook-testing"
Requires-Dist: numba (>=0.56.4) ; extra == "notebook-testing"
Requires-Dist: numpy (>=1.26,<2.0) ; python_version < "3.13"
Requires-Dist: numpy (>=2.1) ; python_version >= "3.13"
Requires-Dist: opencv-python (>=4.6) ; extra == "graphics"
Requires-Dist: opencv-python-headless (>=4.6) ; extra == "headless"
Requires-Dist: protobuf (>=3.2) ; extra == "diffusion"
Requires-Dist: pybsm (>=0.13.0) ; extra == "pybsm"
Requires-Dist: pycocotools (>=2.0.10)
Requires-Dist: pydantic (>=2.6.4) ; extra == "maite"
Requires-Dist: pydantic_settings (>=2.2.1) ; extra == "maite"
Requires-Dist: scikit-image (>=0.20) ; (python_version < "3.12") and (extra == "scikit-image")
Requires-Dist: scikit-image (>=0.22) ; (python_version >= "3.12") and (extra == "scikit-image")
Requires-Dist: scipy (>=1.10.0) ; extra == "waterdroplet"
Requires-Dist: setuptools (>=78.1.1)
Requires-Dist: shapely (>=2.0.7) ; extra == "waterdroplet"
Requires-Dist: smqtk-classifier (>=0.20.0)
Requires-Dist: smqtk-core (>=0.20)
Requires-Dist: smqtk-detection (>=0.23.0)
Requires-Dist: smqtk-image-io (>=0.18.0)
Requires-Dist: tabulate (>=0.9.0) ; extra == "notebook-testing"
Requires-Dist: torch (>=2.2.0) ; extra == "diffusion" or extra == "notebook-testing"
Requires-Dist: torchmetrics (>=1.0.0) ; extra == "notebook-testing"
Requires-Dist: torchvision (>=0.21.0) ; extra == "notebook-testing"
Requires-Dist: tqdm (>=4.64)
Requires-Dist: transformers (>=4.52.1) ; extra == "diffusion" or extra == "notebook-testing"
Requires-Dist: typing-extensions (>=4.5.0)
Requires-Dist: ultralytics (>=8.3.85) ; extra == "notebook-testing"
Requires-Dist: uvicorn (>=0.29.0) ; extra == "maite"
Project-URL: Documentation, https://nrtk.readthedocs.io/
